flow_sensor_RH/__init__.py
flow_sensor_RH/data_process.py
flow_sensor_RH/flow_sensor.py
flow_sensor_RH/get_constant.py
flow_sensor_RH/plot_result.py
flow_sensor_RH/temp_compensation.py
flow_sensor_RH-1.0.0.dist-info/LICENSE
flow_sensor_RH-1.0.0.dist-info/METADATA
flow_sensor_RH-1.0.0.dist-info/WHEEL
flow_sensor_RH-1.0.0.dist-info/top_level.txt
flow_sensor_RH-1.0.0.dist-info/RECORD
